indo/__init__.py
indo/admin.py
indo/apps.py
indo/funcs.py
indo/static/indo/indo.css
indo/static/indo/indo.js
tests/__init__.py
tests/settings.py
tests/tests.py
django_indo-1.0.4.dist-info/LICENSE
django_indo-1.0.4.dist-info/METADATA
django_indo-1.0.4.dist-info/WHEEL
django_indo-1.0.4.dist-info/top_level.txt
django_indo-1.0.4.dist-info/RECORD
